netpro_fortinet_adapter/__init__.py
netpro_fortinet_adapter/adapters/__init__.py
netpro_fortinet_adapter/adapters/FortiGate/__init__.py
netpro_fortinet_adapter/adapters/FortiGate/base.py
netpro_fortinet_adapter/adapters/FortiGate/serializers/__init__.py
netpro_fortinet_adapter/adapters/FortiGate/serializers/base.py
netpro_fortinet_adapter/adapters/FortiGate/v7_0/__init__.py
netpro_fortinet_adapter/adapters/FortiGate/v7_0/api.py
netpro_fortinet_adapter/adapters/FortiGate/v7_2/__init__.py
netpro_fortinet_adapter/adapters/FortiGate/v7_2/api.py
netpro_fortinet_adapter/adapters/FortiGate/v7_4/__init__.py
netpro_fortinet_adapter/adapters/FortiGate/v7_4/api.py
netpro_fortinet_adapter/adapters/FortiGate/v7_6/__init__.py
netpro_fortinet_adapter/adapters/FortiGate/v7_6/api.py
netpro_fortinet_adapter/adapters/FortiGate/v7_6_4/__init__.py
netpro_fortinet_adapter/adapters/FortiGate/v7_6_4/api.py
netpro_fortinet_adapter-1.0.0.dist-info/licenses/LICENSE
netpro_fortinet_adapter-1.0.0.dist-info/METADATA
netpro_fortinet_adapter-1.0.0.dist-info/WHEEL
netpro_fortinet_adapter-1.0.0.dist-info/entry_points.txt
netpro_fortinet_adapter-1.0.0.dist-info/top_level.txt
netpro_fortinet_adapter-1.0.0.dist-info/RECORD
