Metadata-Version: 2.4
Name: netpro_fortinet_adapter
Version: 1.0.0
Summary: Fortinet adapter package for the NetPro automation platform.
Author-email: Joel Loreno <jcloreno@gmail.com>
Project-URL: Homepage, https://github.com/netpro-community/netpro-fortinet-adapter
Project-URL: Issues, https://github.com/netpro-community/netpro-fortinet-adapter/issues
Keywords: netpro,fortinet,fortigate,network-automation,firewall
Classifier: Intended Audience :: System Administrators
Classifier: Intended Audience :: Information Technology
Classifier: Topic :: System :: Networking
Classifier: Topic :: System :: Systems Administration
Classifier: License :: OSI Approved :: GNU Affero General Public License v3
Classifier: Programming Language :: Python
Classifier: Programming Language :: Python :: 3
Classifier: Programming Language :: Python :: 3.10
Classifier: Programming Language :: Python :: 3.11
Classifier: Programming Language :: Python :: 3.12
Requires-Python: >=3.10
License-File: LICENSE
Requires-Dist: netpro-firewall>=1.0
Dynamic: license-file
